levmarq_torch/__init__.py
levmarq_torch-0.0.1.dist-info/LICENSE
levmarq_torch-0.0.1.dist-info/METADATA
levmarq_torch-0.0.1.dist-info/WHEEL
levmarq_torch-0.0.1.dist-info/top_level.txt
levmarq_torch-0.0.1.dist-info/RECORD
