Metadata-Version: 2.1
Name: levmarq-torch
Version: 0.0.1
Summary: Basic PyTorch implementation of the Levenberg-Marquardt algorithm
Author-email: Adam Coogan <dr.adam.coogan@gmail.com>
License: MIT License
Project-URL: homepage, https://github.com/adam-coogan/levmarq-torch
Project-URL: repository, https://github.com/adam-coogan/levmarq-torch
Classifier: Programming Language :: Python :: 3
Classifier: License :: OSI Approved :: MIT License
Classifier: Operating System :: OS Independent
Requires-Python: >=3.7
License-File: LICENSE
Requires-Dist: torch
